cressida/__init__.py
cressida-0.0.0.dist-info/METADATA
cressida-0.0.0.dist-info/WHEEL
cressida-0.0.0.dist-info/top_level.txt
cressida-0.0.0.dist-info/RECORD
